odoo_mcp_server/__init__.py
odoo_mcp_server/server.py
mcp_server_for_odoo_drk-0.1.4.dist-info/METADATA
mcp_server_for_odoo_drk-0.1.4.dist-info/WHEEL
mcp_server_for_odoo_drk-0.1.4.dist-info/entry_points.txt
mcp_server_for_odoo_drk-0.1.4.dist-info/top_level.txt
mcp_server_for_odoo_drk-0.1.4.dist-info/RECORD
