Metadata-Version: 2.4
Name: mcp-server-for-odoo-drk
Version: 0.1.4
Summary: Odoo MCP Server - Access and manage Odoo data through MCP protocol
Project-URL: Homepage, https://github.com/yourusername/mcp-server-for-odoo-drk
Project-URL: Repository, https://github.com/yourusername/mcp-server-for-odoo-drk
Requires-Python: >=3.12
Requires-Dist: fastmcp>=2.10.6
Requires-Dist: google-genai>=1.27.0
Requires-Dist: mcp>=1.12.2
Requires-Dist: odoorpc>=0.10.1
Requires-Dist: requests>=2.32.4
Provides-Extra: dev
Requires-Dist: pytest; extra == "dev"
Requires-Dist: black; extra == "dev"
Requires-Dist: ruff; extra == "dev"
